django_softdelete_it-0.1.dist-info/top_level.txt
django_softdelete_it-0.1.dist-info/WHEEL
django_softdelete_it-0.1.dist-info/METADATA
django_softdelete_it-0.1.dist-info/metadata.json
django_softdelete_it-0.1.dist-info/DESCRIPTION.rst
django_softdelete_it-0.1.dist-info/RECORD
soft_delete_it/__init__.py
soft_delete_it/models.py
