Metadata-Version: 2.0
Name: django-softdelete-it
Version: 0.1
Summary: A simple Django app to add soft-delete functionality to                 desired models
Home-page: https://github.com/exploreshaifali/django-softdelete-it
Author: Shaifali Agrawal
Author-email: agrawalshaifali09@gmail.com
License: MIT License
Platform: UNKNOWN
Classifier: Environment :: Web Environment
Classifier: Framework :: Django
Classifier: Framework :: Django :: 1.8
Classifier: Framework :: Django :: 1.9
Classifier: Intended Audience :: Developers
Classifier: License :: OSI Approved :: MIT License
Classifier: Operating System :: OS Independent
Classifier: Programming Language :: Python :: 3.5
